_examples/__init__.py
_examples/async_dispatcher_example.py
_examples/async_llm_example.py
_examples/broker_as_tool.py
_examples/broker_examples.py
_examples/broker_image_examples.py
_examples/characterize_ollama.py
_examples/characterize_openai.py
_examples/chat_session.py
_examples/chat_session_with_tool.py
_examples/coding_file_tool.py
_examples/current_datetime_tool_example.py
_examples/design_analysis.py
_examples/embeddings.py
_examples/ensures_files_exist.py
_examples/ephemeral_task_manager_example.py
_examples/fetch_openai_models.py
_examples/file_deduplication.py
_examples/file_tool.py
_examples/image_analysis.py
_examples/image_broker.py
_examples/image_broker_splat.py
_examples/iterative_solver.py
_examples/list_models.py
_examples/model_characterization.py
_examples/openai_gateway_enhanced_demo.py
_examples/oversized_embeddings.py
_examples/raw.py
_examples/react.py
_examples/recursive_agent.py
_examples/routed_send_response.py
_examples/simple_llm.py
_examples/simple_llm_repl.py
_examples/simple_structured.py
_examples/simple_tool.py
_examples/solver_chat_session.py
_examples/streaming.py
_examples/tell_user_example.py
_examples/tracer_demo.py
_examples/tracer_qt_viewer.py
_examples/working_memory.py
_examples/react/__init__.py
_examples/react/formatters.py
_examples/react/agents/__init__.py
_examples/react/agents/decisioning_agent.py
_examples/react/agents/thinking_agent.py
_examples/react/models/__init__.py
_examples/react/models/base.py
_examples/react/models/events.py
mojentic/__init__.py
mojentic/async_dispatcher.py
mojentic/async_dispatcher_spec.py
mojentic/dispatcher.py
mojentic/event.py
mojentic/router.py
mojentic/router_spec.py
mojentic/agents/__init__.py
mojentic/agents/agent_broker.py
mojentic/agents/async_aggregator_agent.py
mojentic/agents/async_aggregator_agent_spec.py
mojentic/agents/async_llm_agent.py
mojentic/agents/async_llm_agent_spec.py
mojentic/agents/base_agent.py
mojentic/agents/base_async_agent.py
mojentic-0.9.0.dist-info/licenses/LICENSE.md
mojentic-0.9.0.dist-info/METADATA
mojentic-0.9.0.dist-info/WHEEL
mojentic-0.9.0.dist-info/top_level.txt
mojentic-0.9.0.dist-info/RECORD
