Metadata-Version: 2.4
Name: mojentic
Version: 0.9.0
Summary: Mojentic is an agentic framework that aims to provide a simple and flexible way to assemble teams of agents to solve complex problems.
Author-email: Stacey Vetzal <stacey@vetzal.com>
Project-URL: Homepage, https://github.com/svetzal/mojentic
Project-URL: Issues, https://github.com/svetzal/mojentic/issues
Classifier: Programming Language :: Python :: 3
Classifier: License :: OSI Approved :: MIT License
Classifier: Operating System :: OS Independent
Requires-Python: >=3.11
License-File: LICENSE.md
Requires-Dist: pydantic
Requires-Dist: structlog
Requires-Dist: numpy
Requires-Dist: ollama
Requires-Dist: openai
Requires-Dist: anthropic
Requires-Dist: tiktoken
Requires-Dist: parsedatetime
Requires-Dist: pytz
Requires-Dist: serpapi
Requires-Dist: colorama
Provides-Extra: dev
Requires-Dist: pytest>=7.0.0; extra == "dev"
Requires-Dist: pytest-asyncio; extra == "dev"
Requires-Dist: pytest-spec; extra == "dev"
Requires-Dist: pytest-cov; extra == "dev"
Requires-Dist: pytest-mock>=3.10.0; extra == "dev"
Requires-Dist: flake8>=6.0.0; extra == "dev"
Requires-Dist: bandit>=1.7.0; extra == "dev"
Requires-Dist: pip-audit>=2.0.0; extra == "dev"
Requires-Dist: mkdocs; extra == "dev"
Requires-Dist: mkdocs-material; extra == "dev"
Requires-Dist: mkdocs-llmstxt; extra == "dev"
Requires-Dist: mkdocstrings[python]; extra == "dev"
Requires-Dist: griffe-fieldz; extra == "dev"
Requires-Dist: pymdown-extensions; extra == "dev"
Dynamic: license-file
